plexomatic/__init__.py
plexomatic/cli.py
plexomatic/cli_ui.py
plexomatic/api/__init__.py
plexomatic/api/anidb_client.py
plexomatic/api/llm_client.py
plexomatic/api/tmdb_client.py
plexomatic/api/tvdb_client.py
plexomatic/api/tvmaze_client.py
plexomatic/config/__init__.py
plexomatic/config/config_manager.py
plexomatic/core/__init__.py
plexomatic/core/backup_system.py
plexomatic/core/constants.py
plexomatic/core/file_scanner.py
plexomatic/core/models.py
plexomatic/metadata/__init__.py
plexomatic/metadata/fetcher.py
plexomatic/metadata/manager.py
plexomatic/templates/anime.template
plexomatic/templates/anime_special.template
plexomatic/templates/general.template
plexomatic/templates/movie.template
plexomatic/templates/tv_show.template
plexomatic/templates/tv_special.template
plexomatic/utils/__init__.py
plexomatic/utils/default_formatters.py
plexomatic/utils/episode_handler.py
plexomatic/utils/file_ops.py
plexomatic/utils/file_utils.py
plexomatic/utils/media_type_compat.py
plexomatic/utils/multi_episode_formatter.py
plexomatic/utils/name_parser.py
plexomatic/utils/name_utils.py
plexomatic/utils/preview_system.py
plexomatic/utils/safe_cast.py
plexomatic/utils/template_formatter.py
plexomatic/utils/template_manager.py
plexomatic/utils/template_registry.py
plexomatic/utils/template_types.py
plexomatic/utils/templates/custom/custom.template
plexomatic/utils/templates/default/anime.template
plexomatic/utils/templates/default/movie.template
plexomatic/utils/templates/default/tv_show.template
plex_o_matic-0.3.2.dist-info/METADATA
plex_o_matic-0.3.2.dist-info/WHEEL
plex_o_matic-0.3.2.dist-info/entry_points.txt
plex_o_matic-0.3.2.dist-info/licenses/LICENSE
plex_o_matic-0.3.2.dist-info/RECORD
