Metadata-Version: 2.4
Name: plex-o-matic
Version: 0.3.2
Summary: An intelligent media file organization tool for Plex
Author-email: Douglas MacKrell <your.email@example.com>
License:                     GNU GENERAL PUBLIC LICENSE
License-File: LICENSE
Requires-Python: >=3.8
Requires-Dist: click>=8.1.0
Requires-Dist: pathlib>=1.0.1
Requires-Dist: python-dotenv>=1.0.0
Requires-Dist: pyyaml>=6.0.1
Requires-Dist: requests>=2.31.0
Requires-Dist: rich>=13.0.0
Requires-Dist: sqlalchemy>=2.0.0
Requires-Dist: typing-extensions>=4.0.0
Provides-Extra: dev
Requires-Dist: black>=23.7.0; extra == 'dev'
Requires-Dist: mypy>=1.5.1; extra == 'dev'
Requires-Dist: ruff>=0.0.284; extra == 'dev'
Provides-Extra: test
Requires-Dist: pytest-cov>=4.1.0; extra == 'test'
Requires-Dist: pytest-mock>=3.11.1; extra == 'test'
Requires-Dist: pytest>=7.4.0; extra == 'test'
